flashrank/Config.py
flashrank/Ranker.py
flashrank/__init__.py
FlashRank-0.2.10.dist-info/LICENSE
FlashRank-0.2.10.dist-info/METADATA
FlashRank-0.2.10.dist-info/WHEEL
FlashRank-0.2.10.dist-info/top_level.txt
FlashRank-0.2.10.dist-info/RECORD
