Metadata-Version: 2.1
Name: FlashRank
Version: 0.2.10
Summary: Ultra lite & Super fast SoTA cross-encoder based re-ranking for your search & retrieval pipelines.
Home-page: https://github.com/PrithivirajDamodaran/FlashRank
Author: Prithivi Da
Author-email: 
License: Apache 2.0
Classifier: Programming Language :: Python :: 3
Classifier: License :: OSI Approved :: Apache Software License
Classifier: Operating System :: OS Independent
Requires-Python: >=3.6
Provides-Extra: listwise
License-File: LICENSE
